{"cameraMode":{"drawMode":0,"name":"Shaded","section":"Shading Mode"},"sceneLighting":false,"audioPlay":false,"sceneViewState":{"showFog":true,"showMaterialUpdate":false,"showSkybox":false,"showFlares":true,"showImageEffects":true,"showParticleSystems":true},"in2DMode":false,"pivot":{"x":338.9560546875,"y":1905.132080078125,"z":19.14535140991211},"rotation":{"x":0.017988475039601327,"y":-0.012031379155814648,"z":-0.00019833783153444529,"w":-0.9997984766960144},"size":805.4791870117188,"orthographic":false}