{"cameraMode":{"drawMode":0,"name":"Shaded","section":"Shading Mode"},"sceneLighting":false,"audioPlay":false,"sceneViewState":{"showFog":true,"showMaterialUpdate":false,"showSkybox":false,"showFlares":true,"showImageEffects":true,"showParticleSystems":true},"in2DMode":false,"pivot":{"x":-28.019466400146486,"y":-4.566610813140869,"z":1114.3060302734375},"rotation":{"x":0.15237481892108918,"y":-0.7320331335067749,"z":0.1740206629037857,"w":0.6408553719520569},"size":83.11726379394531,"orthographic":false}