{"cameraMode":{"drawMode":0,"name":"Shaded","section":"Shading Mode"},"sceneLighting":false,"audioPlay":false,"sceneViewState":{"showFog":true,"showMaterialUpdate":false,"showSkybox":false,"showFlares":true,"showImageEffects":true,"showParticleSystems":true},"in2DMode":false,"pivot":{"x":-0.19846418499946595,"y":1.3728604316711426,"z":2.0079715251922609},"rotation":{"x":-0.017690468579530717,"y":-0.007193050812929869,"z":-0.00010708014451665804,"w":0.9998980164527893},"size":3.2076480388641359,"orthographic":false}